paperfig/__init__.py
paperfig/cli.py
paperfig/figure.py
paperfig-0.2.0.dist-info/METADATA
paperfig-0.2.0.dist-info/WHEEL
paperfig-0.2.0.dist-info/entry_points.txt
paperfig-0.2.0.dist-info/licenses/LICENSE
paperfig-0.2.0.dist-info/RECORD
