Metadata-Version: 2.4
Name: paperfig
Version: 0.2.0
Summary: JSON-driven orchestration for building and concatenating paper figures.
Project-URL: Homepage, https://sekika.github.io/paperfig/
Project-URL: Documentation, https://sekika.github.io/paperfig/
Project-URL: Source, https://github.com/sekika/paperfig
Author: Katsutoshi Seki
License: MIT
License-File: LICENSE
Classifier: Intended Audience :: Science/Research
Classifier: License :: OSI Approved :: MIT License
Classifier: Operating System :: OS Independent
Classifier: Programming Language :: Python :: 3
Classifier: Programming Language :: Python :: 3 :: Only
Classifier: Topic :: Scientific/Engineering :: Visualization
Requires-Python: >=3.9
Requires-Dist: pdfgridcat>=1.0.0
Provides-Extra: examples
Requires-Dist: matplotlib>=3.5; extra == 'examples'
Requires-Dist: numpy>=1.22; extra == 'examples'
